Geofront-0.4.0.dist-info/DESCRIPTION.rst
Geofront-0.4.0.dist-info/METADATA
Geofront-0.4.0.dist-info/RECORD
Geofront-0.4.0.dist-info/WHEEL
Geofront-0.4.0.dist-info/entry_points.txt
Geofront-0.4.0.dist-info/metadata.json
Geofront-0.4.0.dist-info/top_level.txt
geofront/__init__.py
geofront/identity.py
geofront/keystore.py
geofront/masterkey.py
geofront/regen.py
geofront/remote.py
geofront/server.py
geofront/team.py
geofront/version.py
geofront/backends/__init__.py
geofront/backends/bitbucket.py
geofront/backends/cloud.py
geofront/backends/dbapi.py
geofront/backends/github.py
geofront/backends/oauth.py
geofront/backends/stash.py
tests/backends/__init__.py
tests/backends/bitbucket_test.py
tests/backends/cloud_test.py
tests/backends/dbapi_test.py
tests/backends/github_test.py
