Metadata-Version: 2.0
Name: Geofront
Version: 0.4.0
Summary: Simple SSH key management service
Home-page: https://github.com/spoqa/geofront
Author: Spoqa
Author-email: dev@spoqa.com
License: AGPLv3 or later
Platform: UNKNOWN
Classifier: Development Status :: 4 - Beta
Classifier: Environment :: Web Environment
Classifier: Intended Audience :: Developers
Classifier: Intended Audience :: System Administrators
Classifier: License :: OSI Approved :: GNU Affero General Public License v3 or later (AGPLv3+)
Classifier: Operating System :: POSIX
Classifier: Programming Language :: Python :: 3
Classifier: Programming Language :: Python :: 3.3
Classifier: Programming Language :: Python :: 3.4
Classifier: Programming Language :: Python :: 3.5
Classifier: Programming Language :: Python :: 3.6
Classifier: Programming Language :: Python :: Implementation :: CPython
Classifier: Topic :: Internet :: WWW/HTTP :: WSGI :: Application
Classifier: Topic :: System :: Systems Administration :: Authentication/Directory
Requires-Python: >=3.3.0
Requires-Dist: Flask (>=0.10.1)
Requires-Dist: Werkzeug (>=0.11)
Requires-Dist: apache-libcloud (>=1.1.0)
Requires-Dist: cryptography (>=1.4)
Requires-Dist: oauthlib[rsa,signedtoken] (>=1.1.1,<2.0.0)
Requires-Dist: paramiko (>=2.0.1)
Requires-Dist: setuptools
Requires-Dist: typeguard (>=2.1.1,<3.0.0)
Requires-Dist: waitress (>=1.0.2,<2.0.0)
Requires-Dist: singledispatch; python_version=='3.3'
Requires-Dist: typing; python_version=='3.3'
Requires-Dist: typing; python_version=='3.4'
Provides-Extra: docs
Requires-Dist: Sphinx (>=1.2); extra == 'docs'
Requires-Dist: sphinxcontrib-autoprogram; extra == 'docs'
Requires-Dist: sphinxcontrib-httpdomain (>=1.2.1); extra == 'docs'
Provides-Extra: tests
Requires-Dist: iso8601 (>=0.1.10); extra == 'tests'
Requires-Dist: pytest (>=2.5.0); extra == 'tests'
Requires-Dist: pytest-cov; extra == 'tests'
Requires-Dist: redis; extra == 'tests'
Requires-Dist: sftpserver (==0.2setuptools); extra == 'tests'
